tappipe/__init__.py
tappipe/cmd_resp.py
tappipe/crc.py
tappipe/enums.py
tappipe/frame.py
tappipe/node_table.py
tappipe/parser.py
tappipe/power_report.py
tappipe/recv_resp.py
tappipe/topology_report.py
tappipe-0.0.5.dist-info/LICENSE
tappipe-0.0.5.dist-info/METADATA
tappipe-0.0.5.dist-info/WHEEL
tappipe-0.0.5.dist-info/top_level.txt
tappipe-0.0.5.dist-info/RECORD
